aleksis/apps/resint/__init__.py
aleksis/apps/resint/admin.py
aleksis/apps/resint/apps.py
aleksis/apps/resint/forms.py
aleksis/apps/resint/frontend/index.js
aleksis/apps/resint/frontend/messages/ar.json
aleksis/apps/resint/frontend/messages/de.json
aleksis/apps/resint/frontend/messages/en.json
aleksis/apps/resint/frontend/messages/fr.json
aleksis/apps/resint/frontend/messages/la.json
aleksis/apps/resint/frontend/messages/nb_NO.json
aleksis/apps/resint/frontend/messages/ru.json
aleksis/apps/resint/frontend/messages/tr.json
aleksis/apps/resint/frontend/messages/uk.json
aleksis/apps/resint/locale/ar/LC_MESSAGES/django.mo
aleksis/apps/resint/locale/ar/LC_MESSAGES/django.po
aleksis/apps/resint/locale/de_DE/LC_MESSAGES/django.mo
aleksis/apps/resint/locale/de_DE/LC_MESSAGES/django.po
aleksis/apps/resint/locale/fr/LC_MESSAGES/django.mo
aleksis/apps/resint/locale/fr/LC_MESSAGES/django.po
aleksis/apps/resint/locale/la/LC_MESSAGES/django.mo
aleksis/apps/resint/locale/la/LC_MESSAGES/django.po
aleksis/apps/resint/locale/nb_NO/LC_MESSAGES/django.mo
aleksis/apps/resint/locale/nb_NO/LC_MESSAGES/django.po
aleksis/apps/resint/locale/ru/LC_MESSAGES/django.mo
aleksis/apps/resint/locale/ru/LC_MESSAGES/django.po
aleksis/apps/resint/locale/tr_TR/LC_MESSAGES/django.mo
aleksis/apps/resint/locale/tr_TR/LC_MESSAGES/django.po
aleksis/apps/resint/locale/uk/LC_MESSAGES/django.mo
aleksis/apps/resint/locale/uk/LC_MESSAGES/django.po
aleksis/apps/resint/migrations/0001_initial.py
aleksis/apps/resint/migrations/0002_permissions.py
aleksis/apps/resint/migrations/0003_group_in_unique_constraint.py
aleksis/apps/resint/migrations/0004_edit_permission.py
aleksis/apps/resint/migrations/0005_fix_permissions.py
aleksis/apps/resint/migrations/0006_livedocument.py
aleksis/apps/resint/migrations/0007_current_file_not_null.py
aleksis/apps/resint/migrations/0008_public_live_documents.py
aleksis/apps/resint/migrations/0009_managed_by_app_label.py
aleksis/apps/resint/migrations/0010_drop_site.py
aleksis_app_resint-4.0.0.dist-info/LICENCE.rst
aleksis_app_resint-4.0.0.dist-info/METADATA
aleksis_app_resint-4.0.0.dist-info/WHEEL
aleksis_app_resint-4.0.0.dist-info/entry_points.txt
aleksis_app_resint-4.0.0.dist-info/RECORD
