Metadata-Version: 2.3
Name: AlekSIS-App-Resint
Version: 4.0.0
Summary: AlekSIS (School Information System) — App Resint (Public poster)
License: EUPL-1.2-or-later
Author: Julian Leucker
Author-email: leuckeju@katharineum.de
Maintainer: Jonathan Weth
Maintainer-email: jonathan.weth@teckids.org
Requires-Python: >=3.10,<4.0
Classifier: Development Status :: 5 - Production/Stable
Classifier: Environment :: Web Environment
Classifier: Intended Audience :: Education
Classifier: License :: Other/Proprietary License
Classifier: Programming Language :: Python :: 3
Classifier: Programming Language :: Python :: 3.10
Classifier: Programming Language :: Python :: 3.11
Classifier: Programming Language :: Python :: 3.12
Classifier: Programming Language :: Python :: 3.13
Classifier: Topic :: Education
Requires-Dist: AlekSIS-Core (>=4.0.0,<5.0.0)
Project-URL: Homepage, https://aleksis.org
Project-URL: Repository, https://edugit.org/AlekSIS/official/AlekSIS-App-Resint
